Burbuja/__init__.py
Burbuja/burbuja.py
Burbuja/modules/__init__.py
Burbuja/modules/base.py
Burbuja/modules/parse.py
Burbuja/modules/structures.py
Burbuja/tests/__init__.py
Burbuja/tests/test_compare.py
Burbuja/tests/test_systems.py
burbuja-1.0.3.dist-info/licenses/LICENSE
burbuja-1.0.3.dist-info/METADATA
burbuja-1.0.3.dist-info/WHEEL
burbuja-1.0.3.dist-info/entry_points.txt
burbuja-1.0.3.dist-info/top_level.txt
burbuja-1.0.3.dist-info/RECORD
