Metadata-Version: 2.4
Name: burbuja
Version: 1.0.3
Summary: Bubble detection for molecular dynamics simulations.
Author-email: Abraham Muñiz Chicharro <abrahanmuniz@gmail.com>, Lane Votapka <lvotapka100@gmail.com>
License-Expression: MIT
Project-URL: Source, https://github.com/Abrahammc90/Burbuja.git
Project-URL: Documentation, https://burbuja.readthedocs.io/
Classifier: Programming Language :: Python :: 3
Requires-Python: >=3.10
License-File: LICENSE
Requires-Dist: numpy
Requires-Dist: attrs
Requires-Dist: mdtraj
Requires-Dist: pytest>=7.2
Provides-Extra: test
Requires-Dist: pytest>=7.2; extra == "test"
Dynamic: license-file
